HISTORY.md
LICENSE
MANIFEST.in
README.md
requirements.txt
setup.py
bitflyer/__init__.py
bitflyer/private.py
bitflyer/public.py
bitflyer/utils.py
bitflyer.egg-info/PKG-INFO
bitflyer.egg-info/SOURCES.txt
bitflyer.egg-info/dependency_links.txt
bitflyer.egg-info/not-zip-safe
bitflyer.egg-info/requires.txt
bitflyer.egg-info/top_level.txt