Metadata-Version: 1.1
Name: bitflyer
Version: 0.0.1
Summary: Bitflyer API Library for Python
Home-page: https://github.com/kmn/bitflyer
Author: Shohei Kamon
Author-email: kamonshohei@gmail.com
License: MIT
Platform: UNKNOWN
Classifier: Development Status :: 5 - Production/Stable
Classifier: Intended Audience :: Developers
Classifier: Natural Language :: English
Classifier: License :: OSI Approved :: MIT License
Classifier: Programming Language :: Python
Classifier: Programming Language :: Python :: 2.7
Classifier: Programming Language :: Python :: 3
Classifier: Programming Language :: Python :: 3.3
